{
  "name": "opuscodium-dehydrated",
  "version": "9.0.1-rc0",
  "author": "Opus Codium",
  "summary": "Manages Let's encrypt certificates using dehydrated",
  "license": "MIT",
  "source": "https://github.com/opus-codium/puppet-dehydrated",
  "project_page": "https://github.com/opus-codium/puppet-dehydrated",
  "issues_url": "https://github.com/opus-codium/puppet-dehydrated/issues",
  "dependencies": [
    {
      "name": "puppetlabs/concat",
      "version_requirement": ">= 2.1.0 < 10.0.0"
    },
    {
      "name": "puppetlabs/ruby_task_helper",
      "version_requirement": ">= 0.6.0 < 2.0.0"
    },
    {
      "name": "puppetlabs/stdlib",
      "version_requirement": ">= 9.0.0 < 10.0.0"
    }
  ],
  "operatingsystem_support": [
    {
      "operatingsystem": "Debian",
      "operatingsystemrelease": [
        "10",
        "11",
        "12",
        "13"
      ]
    },
    {
      "operatingsystem": "FreeBSD",
      "operatingsystemrelease": [
        "11",
        "12",
        "13",
        "14",
        "15"
      ]
    },
    {
      "operatingsystem": "Ubuntu",
      "operatingsystemrelease": [
        "18.04",
        "20.04",
        "22.04",
        "24.04"
      ]
    }
  ],
  "requirements": [
    {
      "name": "openvox",
      "version_requirement": ">= 8.19.0 < 9.0.0"
    }
  ],
  "description": "The dehydrated module lets you use Puppet to manage Let's Encrypt certificates creation and renewal using dehydrated."
}
